pymy/__init__.py
pymy/create.py
pymy/execute.py
pymy/mysql_credentials.py
pymy/send.py
pymy-0.0.8.dist-info/DESCRIPTION.rst
pymy-0.0.8.dist-info/METADATA
pymy-0.0.8.dist-info/RECORD
pymy-0.0.8.dist-info/WHEEL
pymy-0.0.8.dist-info/metadata.json
pymy-0.0.8.dist-info/top_level.txt
