Metadata-Version: 2.0
Name: pymy
Version: 0.0.8
Summary: Easily send data to MySQL
Home-page: https://github.com/dacker-team/pyred
Author: Dacker
Author-email: hello@dacker.co
License: Copyright (c) 2019, Dacker
Requires-Dist: pymysql (>=0.9.3)
Requires-Dist: sshtunnel (==0.1.4)
